graphqldb/__init__.py
graphqldb/adapter.py
graphqldb/db_engine_specs.py
graphqldb/dialect.py
graphqldb/lib.py
graphqldb/types.py
hakurei_sqlalchemy_graphqlapi-0.0.1.dev24.dist-info/LICENSE
hakurei_sqlalchemy_graphqlapi-0.0.1.dev24.dist-info/METADATA
hakurei_sqlalchemy_graphqlapi-0.0.1.dev24.dist-info/WHEEL
hakurei_sqlalchemy_graphqlapi-0.0.1.dev24.dist-info/entry_points.txt
hakurei_sqlalchemy_graphqlapi-0.0.1.dev24.dist-info/top_level.txt
hakurei_sqlalchemy_graphqlapi-0.0.1.dev24.dist-info/RECORD
