Metadata-Version: 2.1
Name: hakurei-sqlalchemy-graphqlapi
Version: 0.0.1.dev24
Summary: Python DB-API and SQLAlchemy interface for GraphQL APIs.
Home-page: https://github.com/cancan101/graphql-db-api
Author: Alex Rothberg
Author-email: agrothberg@gmail.com
License: MIT
Platform: UNKNOWN
Classifier: Development Status :: 2 - Pre-Alpha
Classifier: License :: OSI Approved :: MIT License
Classifier: Programming Language :: Python
Classifier: Programming Language :: Python :: 3.7
Classifier: Programming Language :: Python :: 3.8
Classifier: Programming Language :: Python :: 3.9
Classifier: Programming Language :: Python :: 3.10
Classifier: Programming Language :: Python :: Implementation :: CPython
License-File: LICENSE
Requires-Dist: shillelagh (>=1.0.6)
Requires-Dist: sqlalchemy (>=1.3.0)
Requires-Dist: requests (>=2.20.0)
Requires-Dist: typing-extensions
